covidsafescan/__main__.py
covidsafescan/host.py
covidsafescan-1.14.dist-info/LICENSE.md
covidsafescan-1.14.dist-info/METADATA
covidsafescan-1.14.dist-info/WHEEL
covidsafescan-1.14.dist-info/entry_points.txt
covidsafescan-1.14.dist-info/top_level.txt
covidsafescan-1.14.dist-info/RECORD
