Metadata-Version: 2.1
Name: covidsafescan
Version: 1.14
Summary: Covid Safe Scanner
Home-page: https://github.com/xssfox/covidsafescan
Author: xssfox
Author-email: pypi@sprocketfox.io
License: UNKNOWN
Platform: UNKNOWN
Requires-Dist: bleak
